[
    {
        "id": "urn:ngsi:AirQualityObserved:KielRegion:Oppendorf",
        "type": "AirQualityObserved",
        "name": "Luftqualität",
        "description": "Luftqualität Bahnhof Oppendorf",
        "location": {
            "type": "Point",
            "coordinates": [10.208026, 54.326155]
        },
        "dateObserved": "2021-03-01T01:02:03.00Z",
        "refWheatherObserved": "urn:ngsi:WeatherObserved:KielRegion:Oppendorf",
        "pm10": 43.21,
        "pm25": 12.34,
        "refDevice": ""
    }
]
